mcp_first_tool_server/__init__.py
mcp_first_tool_server/__main__.py
mcp_first_tool_server/server.py
mcp_first_tool_server-0.1.0.dist-info/METADATA
mcp_first_tool_server-0.1.0.dist-info/WHEEL
mcp_first_tool_server-0.1.0.dist-info/entry_points.txt
mcp_first_tool_server-0.1.0.dist-info/top_level.txt
mcp_first_tool_server-0.1.0.dist-info/RECORD
