Metadata-Version: 2.4
Name: mcp-first-tool-server
Version: 0.1.0
Summary: Add your description here
Requires-Python: >=3.12
Requires-Dist: dotenv>=0.9.9
Requires-Dist: asyncio>=3.4.3
Requires-Dist: mcp>=1.6.0
Requires-Dist: openai>=1.75.0
Requires-Dist: openai-agents>=0.0.12
Requires-Dist: pydantic>=2.11.3
Requires-Dist: typing>=3.10.0.0
